{
    "bg": "http://www.yeebaplay.com.br/blog/wp-content/uploads/2015/05/css3.jpg",
    "title":"Quizz CSS Tricquiz",
    "description": "Venha testar seus conhecimentos em CSS!",
    "questions": [
        {
            "image": "",
            "title": "",
            "description": "",
            "answer":"",
            "alternatives": []
        },
        {
            "image": "",
            "title": "",
            "description": "",
            "answer":"",
            "alternatives": []
        }
    ],
    "external": [

    ],
    "theme": {
        "colors": {
            "primary": "#502274",
            "secondary": "#a29bfe",
            "mainBg": "#2F242C",
            "lightText": "#F7FFF7",
            "darkText": "#353535",
            "wrong": "#FF5722",
            "success": "#4CAF50",
            "button": "#A42CD6",
            "disabled": "#d9d9d9"
        },
        "borderRadius": "4px"
    }
}